[{"tasksTitle":"Task title is stored here","timeStamp":""},{"tasksTitle":"Dsfdsf","time":1589871080000,"taskDeadline":"","taskDeadlineTime":"","taskPriority":"mp","taskSubtasks":[{"sTask":"fdakshfkj","completed":0},{"sTask":"dfkljadslk","completed":0}],"taskComments":[],"completed":0},{"tasksTitle":"Dsfadf","time":1589872513000,"taskDeadline":"","taskDeadlineTime":"","taskPriority":"","taskSubtasks":[],"taskComments":[],"completed":0},{"tasksTitle":"Asdfadsf","time":1589872514000,"taskDeadline":"","taskDeadlineTime":"","taskPriority":"hp","taskSubtasks":[],"taskComments":[],"completed":0},{"tasksTitle":"Efewf","time":1589872713000,"taskDeadline":"","taskDeadlineTime":"","taskPriority":"lp","taskSubtasks":[],"taskComments":[],"completed":0},{"tasksTitle":"Sdfdsfnkhdsg","time":1589873593000,"taskDeadline":"","taskDeadlineTime":"","taskPriority":"mp","taskSubtasks":[],"taskComments":[],"completed":0}]